quickshare/__init__.py
quickshare/cli.py
quickshare/control.py
quickshare/discovery.py
quickshare/fileutils.py
quickshare/transfer.py
quickshare_py-1.0.8.dist-info/licenses/LICENSE
quickshare_py-1.0.8.dist-info/METADATA
quickshare_py-1.0.8.dist-info/WHEEL
quickshare_py-1.0.8.dist-info/entry_points.txt
quickshare_py-1.0.8.dist-info/top_level.txt
quickshare_py-1.0.8.dist-info/RECORD
