Metadata-Version: 2.4
Name: quickshare-py
Version: 1.0.8
Summary: Next-generation parallel P2P LAN file transfer
Home-page: https://github.com/GeoAziz/quickshare-py
Author: GeoAziz
License: MIT
Classifier: Programming Language :: Python :: 3
Classifier: License :: OSI Approved :: MIT License
Classifier: Operating System :: OS Independent
Requires-Python: >=3.8
License-File: LICENSE
Requires-Dist: qrcode
Requires-Dist: colorama
Dynamic: license-file
